[
  {
    "UniqueID": 1100101,
    "ActiveRadius": 500,
    "DefaultState": true,
    "WaypointWarpNeedCostId": 0,
    "WaypointWarpNeedCostCount": 0,
    "WaypointWarpNeedItemId": 621000001,
    "WaypointWarpNeedItemCount": 1,
    "WayPointName": 920243,
    "Location": {
      "X": -21415.484,
      "Y": 20516.87,
      "Z": 2588.756
    },
    "WarpCoordinate": {
      "X": -20788.842,
      "Y": 20828.828,
      "Z": 2588.756
    }
  },
  {
    "UniqueID": 1100102,
    "ActiveRadius": 500,
    "DefaultState": true,
    "WaypointWarpNeedCostId": 0,
    "WaypointWarpNeedCostCount": 0,
    "WaypointWarpNeedItemId": 621000001,
    "WaypointWarpNeedItemCount": 1,
    "WayPointName": 920244,
    "Location": {
      "X": -3282.86,
      "Y": 19530.047,
      "Z": 4123.187
    },
    "WarpCoordinate": {
      "X": -2656.217,
      "Y": 19842.006,
      "Z": 4123.187
    }
  },
  {
    "UniqueID": 1100103,
    "ActiveRadius": 500,
    "DefaultState": true,
    "WaypointWarpNeedCostId": 0,
    "WaypointWarpNeedCostCount": 0,
    "WaypointWarpNeedItemId": 621000001,
    "WaypointWarpNeedItemCount": 1,
    "WayPointName": 920245,
    "Location": {
      "X": -3874.607,
      "Y": -3822.647,
      "Z": 1208.063
    },
    "WarpCoordinate": {
      "X": -3765.464,
      "Y": -4514.086,
      "Z": 1208.063
    }
  },
  {
    "UniqueID": 1100104,
    "ActiveRadius": 500,
    "DefaultState": true,
    "WaypointWarpNeedCostId": 0,
    "WaypointWarpNeedCostCount": 0,
    "WaypointWarpNeedItemId": 621000001,
    "WaypointWarpNeedItemCount": 1,
    "WayPointName": 920246,
    "Location": {
      "X": 12661.05,
      "Y": -161.699,
      "Z": 1886.766
    },
    "WarpCoordinate": {
      "X": 12141.981,
      "Y": -631.346,
      "Z": 1886.766
    }
  },
  {
    "UniqueID": 1100105,
    "ActiveRadius": 500,
    "DefaultState": true,
    "WaypointWarpNeedCostId": 0,
    "WaypointWarpNeedCostCount": 0,
    "WaypointWarpNeedItemId": 621000001,
    "WaypointWarpNeedItemCount": 1,
    "WayPointName": 920286,
    "Location": {
      "X": -19532.818,
      "Y": -21451.143,
      "Z": 2470.568
    },
    "WarpCoordinate": {
      "X": -20051.887,
      "Y": -21920.79,
      "Z": 2470.568
    }
  },
  {
    "UniqueID": 1100106,
    "ActiveRadius": 500,
    "DefaultState": true,
    "WaypointWarpNeedCostId": 0,
    "WaypointWarpNeedCostCount": 0,
    "WaypointWarpNeedItemId": 621000001,
    "WaypointWarpNeedItemCount": 1,
    "WayPointName": 920287,
    "Location": {
      "X": 13733.052,
      "Y": -18996.945,
      "Z": 652.831
    },
    "WarpCoordinate": {
      "X": 13213.983,
      "Y": -19466.592,
      "Z": 652.831
    }
  },
  {
    "UniqueID": 1100201,
    "ActiveRadius": 0,
    "DefaultState": true,
    "WaypointWarpNeedCostId": 0,
    "WaypointWarpNeedCostCount": 0,
    "WaypointWarpNeedItemId": 621000001,
    "WaypointWarpNeedItemCount": 1,
    "WayPointName": 3740026,
    "Location": {
      "X": -12129,
      "Y": -5589,
      "Z": 1914
    },
    "WarpCoordinate": {
      "X": -12129,
      "Y": -5589,
      "Z": 1914
    }
  },
  {
    "UniqueID": 1100202,
    "ActiveRadius": 0,
    "DefaultState": true,
    "WaypointWarpNeedCostId": 0,
    "WaypointWarpNeedCostCount": 0,
    "WaypointWarpNeedItemId": 621000001,
    "WaypointWarpNeedItemCount": 1,
    "WayPointName": 3740064,
    "Location": {
      "X": 9783,
      "Y": -15236,
      "Z": 773
    },
    "WarpCoordinate": {
      "X": 9783,
      "Y": -15236,
      "Z": 773
    }
  },
  {
    "UniqueID": 1100203,
    "ActiveRadius": 0,
    "DefaultState": true,
    "WaypointWarpNeedCostId": 0,
    "WaypointWarpNeedCostCount": 0,
    "WaypointWarpNeedItemId": 621000001,
    "WaypointWarpNeedItemCount": 1,
    "WayPointName": 3750445,
    "Location": {
      "X": 6385,
      "Y": -2138,
      "Z": 1425
    },
    "WarpCoordinate": {
      "X": 6385,
      "Y": -2138,
      "Z": 1425
    }
  },
  {
    "UniqueID": 1100204,
    "ActiveRadius": 0,
    "DefaultState": true,
    "WaypointWarpNeedCostId": 0,
    "WaypointWarpNeedCostCount": 0,
    "WaypointWarpNeedItemId": 621000001,
    "WaypointWarpNeedItemCount": 1,
    "WayPointName": 3740063,
    "Location": {
      "X": -9216,
      "Y": 15682,
      "Z": 3282
    },
    "WarpCoordinate": {
      "X": -9216,
      "Y": 15682,
      "Z": 3282
    }
  },
  {
    "UniqueID": 1100301,
    "ActiveRadius": 500,
    "DefaultState": true,
    "WaypointWarpNeedCostId": 0,
    "WaypointWarpNeedCostCount": 0,
    "WaypointWarpNeedItemId": 621000001,
    "WaypointWarpNeedItemCount": 1,
    "WayPointName": 920300,
    "Location": {
      "X": 15645.729,
      "Y": 18434.496,
      "Z": 4140
    },
    "WarpCoordinate": {
      "X": 15119.416,
      "Y": 16763.447,
      "Z": 4178.147
    }
  },
  {
    "UniqueID": 1100401,
    "ActiveRadius": 0,
    "DefaultState": true,
    "WaypointWarpNeedCostId": 0,
    "WaypointWarpNeedCostCount": 0,
    "WaypointWarpNeedItemId": 621000001,
    "WaypointWarpNeedItemCount": 1,
    "WayPointName": 600629,
    "Location": {
      "X": 18775.455,
      "Y": -13410.409,
      "Z": 2728
    },
    "WarpCoordinate": {
      "X": 18775.455,
      "Y": -13410.409,
      "Z": 2728
    }
  },
  {
    "UniqueID": 11000125,
    "ActiveRadius": 0,
    "DefaultState": true,
    "WaypointWarpNeedCostId": 0,
    "WaypointWarpNeedCostCount": 0,
    "WaypointWarpNeedItemId": 621000001,
    "WaypointWarpNeedItemCount": 1,
    "WayPointName": 2170031,
    "Location": {
      "X": -3450,
      "Y": 4586,
      "Z": 2440
    },
    "WarpCoordinate": {
      "X": -3450,
      "Y": 4586,
      "Z": 2440
    }
  }
]